darkchromasdk/__init__.py
darkchromasdk/chroma_sdk.py
darkchromasdk/color_parsing.py
darkchromasdk-0.0.4.dist-info/LICENSE
darkchromasdk-0.0.4.dist-info/METADATA
darkchromasdk-0.0.4.dist-info/WHEEL
darkchromasdk-0.0.4.dist-info/top_level.txt
darkchromasdk-0.0.4.dist-info/RECORD
