Metadata-Version: 2.1
Name: darkchromasdk
Version: 0.0.4
Summary: A package to interact with razer keyboard lighting in a simple way
Author-email: Dark_Eden <darkedenc9@gmail.com>
Project-URL: Homepage, https://github.com/DarkEden-coding/darkchromasdk
Project-URL: Bug Tracker, https://github.com/DarkEden-coding/darkchromasdk/issues
Classifier: Programming Language :: Python :: 3
Classifier: License :: OSI Approved :: MIT License
Classifier: Operating System :: OS Independent
Requires-Python: >=3.7
License-File: LICENSE
